tox_pyo3/__init__.py
tox_pyo3/plugin.py
tox_pyo3-1.0.0.dist-info/LICENSE
tox_pyo3-1.0.0.dist-info/METADATA
tox_pyo3-1.0.0.dist-info/WHEEL
tox_pyo3-1.0.0.dist-info/entry_points.txt
tox_pyo3-1.0.0.dist-info/top_level.txt
tox_pyo3-1.0.0.dist-info/RECORD
