Metadata-Version: 2.1
Name: tox-pyo3
Version: 1.0.0
Summary: Build a rust extension using PyO3 using tox.
Home-page: https://github.com/thedrow/tox-pyo3
Author: Omer Katz
Author-email: omer.drow@gmail.com
Maintainer: Omer Katz
Maintainer-email: omer.drow@gmail.com
License: BSD-3
Platform: UNKNOWN
Classifier: Development Status :: 5 - Production/Stable
Classifier: Framework :: tox
Classifier: Intended Audience :: Developers
Classifier: Topic :: Software Development :: Testing
Classifier: Programming Language :: Python
Classifier: Programming Language :: Python :: 3
Classifier: Programming Language :: Python :: 3.5
Classifier: Programming Language :: Python :: 3.6
Classifier: Programming Language :: Python :: 3.7
Classifier: Programming Language :: Python :: 3.8
Classifier: Programming Language :: Python :: Implementation :: CPython
Classifier: Operating System :: OS Independent
Classifier: License :: OSI Approved :: BSD License
Requires-Python: >=3.0, !=3.0.*, !=3.1.*, !=3.2.*, !=3.3.*,!=3.4.*
